pypipackage/__init__.py
pypipackage/hello.py
pyp_package-0.1.dist-info/METADATA
pyp_package-0.1.dist-info/WHEEL
pyp_package-0.1.dist-info/top_level.txt
pyp_package-0.1.dist-info/RECORD
