Metadata-Version: 2.1
Name: pyp_package
Version: 0.1
Requires-Dist: numpy>=1.1.1
